emailsanta/__init__.py
emailsanta/emailsanta.py
emailsanta-1.0.4.dist-info/LICENSE
emailsanta-1.0.4.dist-info/METADATA
emailsanta-1.0.4.dist-info/WHEEL
emailsanta-1.0.4.dist-info/top_level.txt
emailsanta-1.0.4.dist-info/RECORD
