Metadata-Version: 2.1
Name: emailsanta
Version: 1.0.4
Summary: Python module to simulate emailing the legendary Christmas character Santa, powered by Alan Kerr's emailSanta.com.
Home-page: https://github.com/fffelix-jan/emailsanta-py
Author: Félix An
Author-email: fffelix.jan.yt@gmail.com
License: AGPLv3
Project-URL: Documentation, https://github.com/fffelix-jan/emailsanta-py
Project-URL: Funding, https://paypal.me/fffelixjan
Project-URL: Source, https://github.com/fffelix-jan/emailsanta-py
Project-URL: Tracker, https://github.com/fffelix-jan/emailsanta-py/issues
Platform: UNKNOWN
Classifier: License :: OSI Approved :: GNU Affero General Public License v3 or later (AGPLv3+)
Classifier: Programming Language :: Python :: 3
Classifier: Operating System :: OS Independent
Classifier: Topic :: Games/Entertainment
Classifier: Topic :: Other/Nonlisted Topic
Requires-Python: >= 3.5
Requires-Dist: bs4
Requires-Dist: html2text
Requires-Dist: requests
